jpn_bpe_tokenizer/__init__.py
jpn_bpe_tokenizer/mecab_bpe_tokenizer.py
jpn_bpe_tokenizer/pre_tokenizers.py
jpn_bpe_tokenizer/trainer.py
Japanese_BPE_Tokenizer-0.1.2.dist-info/LICENSE
Japanese_BPE_Tokenizer-0.1.2.dist-info/METADATA
Japanese_BPE_Tokenizer-0.1.2.dist-info/WHEEL
Japanese_BPE_Tokenizer-0.1.2.dist-info/top_level.txt
Japanese_BPE_Tokenizer-0.1.2.dist-info/RECORD
